html2info/__init__.py
html2info/kaggle.py
html2info/linkedin.py
html2info/types.py
html2info/utils.py
html2info/types/__init__.py
html2info/types/kaggle.py
html2info/types/linkedin.py
html2info-0.2.0.dist-info/METADATA
html2info-0.2.0.dist-info/WHEEL
html2info-0.2.0.dist-info/top_level.txt
html2info-0.2.0.dist-info/RECORD
