Metadata-Version: 2.1
Name: html2info
Version: 0.2.0
Summary: A package to parse raw HTML and return structured information.
Author: Vladimir Iglovikov
Author-email: iglovikov@gmail.com
Classifier: Development Status :: 3 - Alpha
Classifier: Intended Audience :: Developers
Classifier: License :: OSI Approved :: MIT License
Classifier: Operating System :: OS Independent
Classifier: Programming Language :: Python :: 3
Classifier: Programming Language :: Python :: 3.6
Classifier: Programming Language :: Python :: 3.7
Classifier: Programming Language :: Python :: 3.8
Classifier: Programming Language :: Python :: 3.9
Classifier: Programming Language :: Python :: 3.10
Requires-Python: >=3.6
Requires-Dist: beautifulsoup4 (>=4.12.2)
Requires-Dist: markdownify (>=0.11.6)
